{
	"info": {
		"_postman_id": "eb894639-600f-481f-b0df-fb36d6b254ca",
		"name": "Heroes & Villains",
		"schema": "https://schema.getpostman.com/json/collection/v2.1.0/collection.json",
		"_exporter_id": "22861205"
	},
	"item": [
		{
			"name": "GET super by id",
			"protocolProfileBehavior": {
				"disableBodyPruning": true
			},
			"request": {
				"method": "GET",
				"header": [],
				"body": {
					"mode": "raw",
					"raw": "",
					"options": {
						"raw": {
							"language": "json"
						}
					}
				},
				"url": {
					"raw": "http://127.0.0.1:8000/api/supers/1",
					"protocol": "http",
					"host": [
						"127",
						"0",
						"0",
						"1"
					],
					"port": "8000",
					"path": [
						"api",
						"supers",
						"1"
					]
				}
			},
			"response": []
		},
		{
			"name": "POST new super to db",
			"request": {
				"method": "POST",
				"header": [],
				"body": {
					"mode": "raw",
					"raw": "{\r\n    \"name\": \"Superman\",\r\n    \"alter_ego\": \"Clark Kent\",\r\n    \"primary_ability\": \"Super Strength\",\r\n    \"secondary_ability\": \"Flight\",\r\n    \"catchphrase\": \"Up, up, and away!\",\r\n    \"super_type_id\": 1\r\n}",
					"options": {
						"raw": {
							"language": "json"
						}
					}
				},
				"url": {
					"raw": "http://127.0.0.1:8000/api/supers/",
					"protocol": "http",
					"host": [
						"127",
						"0",
						"0",
						"1"
					],
					"port": "8000",
					"path": [
						"api",
						"supers",
						""
					]
				}
			},
			"response": []
		},
		{
			"name": "UPDATE existing super in db",
			"request": {
				"method": "PUT",
				"header": [],
				"body": {
					"mode": "raw",
					"raw": "{\r\n    \"name\": \"Aquaman\",\r\n    \"alter_ego\": \"Water Guy\",\r\n    \"primary_ability\": \"Swimming\",\r\n    \"secondary_ability\": \"Fish call\",\r\n    \"catchphrase\": \"Let's swim\",\r\n    \"super_type_id\": 1\r\n}",
					"options": {
						"raw": {
							"language": "json"
						}
					}
				},
				"url": {
					"raw": "http://127.0.0.1:8000/api/supers/3/",
					"protocol": "http",
					"host": [
						"127",
						"0",
						"0",
						"1"
					],
					"port": "8000",
					"path": [
						"api",
						"supers",
						"3",
						""
					]
				}
			},
			"response": []
		},
		{
			"name": "DELETE super",
			"request": {
				"method": "DELETE",
				"header": [],
				"url": {
					"raw": "http://127.0.0.1:8000/api/supers/1",
					"protocol": "http",
					"host": [
						"127",
						"0",
						"0",
						"1"
					],
					"port": "8000",
					"path": [
						"api",
						"supers",
						"1"
					]
				}
			},
			"response": []
		},
		{
			"name": "GET all supers",
			"request": {
				"method": "GET",
				"header": [],
				"url": {
					"raw": "http://127.0.0.1:8000/api/supers",
					"protocol": "http",
					"host": [
						"127",
						"0",
						"0",
						"1"
					],
					"port": "8000",
					"path": [
						"api",
						"supers"
					]
				}
			},
			"response": []
		},
		{
			"name": "Get super by type",
			"request": {
				"method": "GET",
				"header": [],
				"url": {
					"raw": "http://127.0.0.1:8000/api/supers?type=villian",
					"protocol": "http",
					"host": [
						"127",
						"0",
						"0",
						"1"
					],
					"port": "8000",
					"path": [
						"api",
						"supers"
					],
					"query": [
						{
							"key": "type",
							"value": "villian"
						}
					]
				}
			},
			"response": []
		}
	]
}